kwbar.py
kwbar-1.0.0.dist-info/LICENSE
kwbar-1.0.0.dist-info/METADATA
kwbar-1.0.0.dist-info/WHEEL
kwbar-1.0.0.dist-info/RECORD
