Metadata-Version: 2.1
Name: kwbar
Version: 1.0.0
Summary: Print kwargs as a bar chart.
License: MIT
Author: John Pocock
Author-email: pypi@pocock.io
Requires-Python: >=3.8,<4.0
Classifier: License :: OSI Approved :: MIT License
Classifier: Programming Language :: Python :: 3
Classifier: Programming Language :: Python :: 3.8
Classifier: Programming Language :: Python :: 3.9
Classifier: Programming Language :: Python :: 3.10
Classifier: Programming Language :: Python :: 3.11
Classifier: Programming Language :: Python :: 3.12
